01_game_of_life/conway_cell.sv
`default_nettype none

module conway_cell(clk, rst, ena, state_0, state_d, state_q, neighbors);
  input wire clk;
  input wire rst;
  input wire ena;

  input wire state_0;
  output logic state_d;
  output logic state_q;

  input wire [7:0] neighbors;
  logic [3:0] living_neighbors;
  logic [1:0] a1;
  logic [1:0] b1;
  logic [1:0] c1;
  logic [1:0] d1;
  logic [2:0] a2;
  logic [2:0] b2;
  logic [3:0] a3;
  always_comb begin    
    // hierarchial design (binary tree minimum number of adders)
    // can never overflow because most significant bit is the AND of previous location bit
    // (4x) 1-bit input, 2-bit output
    a1[1] = neighbors[0] & neighbors[1];
    a1[0] = neighbors[0] ^ neighbors[1];
    
    b1[1] = neighbors[2] & neighbors[3];
    b1[0] = neighbors[2] ^ neighbors[3];
    
    c1[1] = neighbors[4] & neighbors[5];
    c1[0] = neighbors[4] ^ neighbors[5];

    d1[1] = neighbors[6] & neighbors[7];
    d1[0] = neighbors[6] ^ neighbors[7];
    
    // (2x) 2-bit input, 3-bit output
    a2[2] = a1[1] & b1[1];
    a2[1] = (a1[0] & b1[0]) | (a1[1]) ^ (b1[1]);
    a2[0] = a1[0] ^ b1[0];

    b2[2] = c1[1] & d1[1];
    b2[1] = (c1[0] & d1[0]) | (c1[1]) ^ (d1[1]);
    b2[0] = c1[0] ^ d1[0];
    
    // (1x) 3-bit input, 4-bit output
    a3[3] = a2[2] & b2[2];
    a3[2] = (a2[1] & b2[1]) | (a2[2]) ^ (b2[2]); 
    a3[1] = (a2[0] & b2[0]) | (a2[1]) ^ (b2[1]);
    a3[0] = a2[0] ^ b2[0];
    
    // $display("%b, %b", state_0, a3);

    state_d = (state_0 & ~a3[3] & ~a3[2] & a3[1] & ~a3[0]) | (~a3[3] & ~a3[2] & a3[1] & a3[0]);
    state_q = ~state_d;
  end

endmodule

01_game_of_life/test_conway_cell.sv
`timescale 1ns / 1ps
`default_nettype none

`define SIMULATION

module test_conway_cell;

  logic clk, rst, ena, state_0;
  logic [7:0] neighbors;
  wire state_d, state_q;

  conway_cell UUT(
    .clk(clk), .rst(rst), .ena(ena),
    .neighbors(neighbors),
    .state_0(1'b1), .state_d(state_d), .state_q(state_q)
  );

  always #5 clk = ~clk; // Toggle a clock every 5 time units.
	

  /*
    Initial blocks are one of the few things in Verilog that actually
    executes sequentially like normal code, and runs at the top of a 
    simulation. This can sometimes work in synthesis... but it's much
    better practice to use proper synchronous reset logic instead!
  */
  initial begin
    // Initialize modules input.
    clk = 0;
    rst = 1; // Start reset in active state.
    ena = 1; // Not testing the ena function in this example (though you should try!)
    state_0 = 0; //literally what the fuck does this do
    
    // Collect all internal variables for waveforms.
    $dumpfile("conway_cell.vcd");
    $dumpvars(0, UUT);
    
    // Wait at least one clock cycle before deasserting reset.
    repeat (2) @(posedge clk);
    rst = 0;
    
    $display("lrud : d : q");
    for (int i = 0; i < 255; i = i + 1) begin
      // Change inputs at a negative edge to avoid setup issues.
      @(negedge clk);
      neighbors = i[7:0];
      @(posedge clk);
      $display("%b : %b: %b", neighbors, state_d, state_q);
    end

    #10;
    $finish; // End the simulation.
	end

endmodule

01_game_of_life/conway_cell.vcd
$date
	Thu Sep 30 16:31:08 2021
$end
$version
	Icarus Verilog
$end
$timescale
	1ps
$end
$scope module test_conway_cell $end
$scope module UUT $end
$var wire 1 ! clk $end
$var wire 1 " ena $end
$var wire 8 # neighbors [7:0] $end
$var wire 1 $ rst $end
$var wire 1 % state_0 $end
$var reg 2 & a1 [1:0] $end
$var reg 3 ' a2 [2:0] $end
$var reg 4 ( a3 [3:0] $end
$var reg 2 ) b1 [1:0] $end
$var reg 3 * b2 [2:0] $end
$var reg 2 + c1 [1:0] $end
$var reg 2 , d1 [1:0] $end
$var reg 1 - state_d $end
$var reg 1 . state_q $end
$upscope $end
$upscope $end
$enddefinitions $end
#0
$dumpvars
x.
x-
bx ,
bx +
bx *
bx )
bx (
bx '
bx &
1%
1$
bx #
1"
0!
$end
#5000
1!
#10000
0!
#15000
0$
1!
#20000
1.
0-
b0 (
b0 *
b0 '
b0 ,
b0 +
b0 )
b0 &
b0 #
0!
#25000
1!
#30000
b1 (
b1 '
b1 &
b1 #
0!
#35000
1!
#40000
b10 #
0!
#45000
1!
#50000
0.
1-
b10 (
b10 '
b10 &
b11 #
0!
#55000
1!
#60000
1.
0-
b1 (
b1 '
b1 )
b0 &
b100 #
0!
#65000
1!
#70000
0.
1-
b10 (
b10 '
b1 &
b101 #
0!
#75000
1!
#80000
b110 #
0!
#85000
1!
#90000
b11 (
b11 '
b10 &
b111 #
0!
#95000
1!
#100000
1.
0-
b1 (
b1 '
b0 &
b1000 #
0!
#105000
1!
#110000
0.
1-
b10 (
b10 '
b1 &
b1001 #
0!
#115000
1!
#120000
b1010 #
0!
#125000
1!
#130000
b11 (
b11 '
b10 &
b1011 #
0!
#135000
1!
#140000
b10 (
b10 '
b10 )
b0 &
b1100 #
0!
#145000
1!
#150000
b11 (
b11 '
b1 &
b1101 #
0!
#155000
1!
#160000
b1110 #
0!
#165000
1!
#170000
1.
0-
b100 (
b100 '
b10 &
b1111 #
0!
#175000
1!
#180000
b1 (
b1 *
b0 '
b1 +
b0 )
b0 &
b10000 #
0!
#185000
1!
#190000
0.
1-
b10 (
b1 '
b1 &
b10001 #
0!
#195000
1!
#200000
b10010 #
0!
#205000
1!
#210000
b11 (
b10 '
b10 &
b10011 #
0!
#215000
1!
#220000
b10 (
b1 '
b1 )
b0 &
b10100 #
0!
#225000
1!
#230000
b11 (
b10 '
b1 &
b10101 #
0!
#235000
1!
#240000
b10110 #
0!
#245000
1!
#250000
b10 (
b11 '
b10 &
b10111 #
0!
#255000
1!
#260000
b1 '
b0 &
b11000 #
0!
#265000
1!
#270000
b11 (
b10 '
b1 &
b11001 #
0!
#275000
1!
#280000
b11010 #
0!
#285000
1!
#290000
b10 (
b11 '
b10 &
b11011 #
0!
#295000
1!
#300000
b11 (
b10 '
b10 )
b0 &
b11100 #
0!
#305000
1!
#310000
b10 (
b11 '
b1 &
b11101 #
0!
#315000
1!
#320000
b11110 #
0!
#325000
1!
#330000
1.
0-
b101 (
b100 '
b10 &
b11111 #
0!
#335000
1!
#340000
b1 (
b0 '
b0 )
b0 &
b100000 #
0!
#345000
1!
#350000
0.
1-
b10 (
b1 '
b1 &
b100001 #
0!
#355000
1!
#360000
b100010 #
0!
#365000
1!
#370000
b11 (
b10 '
b10 &
b100011 #
0!
#375000
1!
#380000
b10 (
b1 '
b1 )
b0 &
b100100 #
0!
#385000
1!
#390000
b11 (
b10 '
b1 &
b100101 #
0!
#395000
1!
#400000
b100110 #
0!
#405000
1!
#410000
b10 (
b11 '
b10 &
b100111 #
0!
#415000
1!
#420000
b1 '
b0 &
b101000 #
0!
#425000
1!
#430000
b11 (
b10 '
b1 &
b101001 #
0!
#435000
1!
#440000
b101010 #
0!
#445000
1!
#450000
b10 (
b11 '
b10 &
b101011 #
0!
#455000
1!
#460000
b11 (
b10 '
b10 )
b0 &
b101100 #
0!
#465000
1!
#470000
b10 (
b11 '
b1 &
b101101 #
0!
#475000
1!
#480000
b101110 #
0!
#485000
1!
#490000
1.
0-
b101 (
b100 '
b10 &
b101111 #
0!
#495000
1!
#500000
0.
1-
b10 (
b10 *
b0 '
b10 +
b0 )
b0 &
b110000 #
0!
#505000
1!
#510000
b11 (
b1 '
b1 &
b110001 #
0!
#515000
1!
#520000
b110010 #
0!
#525000
1!
#530000
1.
0-
b100 (
b10 '
b10 &
b110011 #
0!
#535000
1!
#540000
0.
1-
b11 (
b1 '
b1 )
b0 &
b110100 #
0!
#545000
1!
#550000
1.
0-
b100 (
b10 '
b1 &
b110101 #
0!
#555000
1!
#560000
b110110 #
0!
#565000
1!
#570000
b101 (
b11 '
b10 &
b110111 #
0!
#575000
1!
#580000
0.
1-
b11 (
b1 '
b0 &
b111000 #
0!
#585000
1!
#590000
1.
0-
b100 (
b10 '
b1 &
b111001 #
0!
#595000
1!
#600000
b111010 #
0!
#605000
1!
#610000
b101 (
b11 '
b10 &
b111011 #
0!
#615000
1!
#620000
b100 (
b10 '
b10 )
b0 &
b111100 #
0!
#625000
1!
#630000
b101 (
b11 '
b1 &
b111101 #
0!
#635000
1!
#640000
b111110 #
0!
#645000
1!
#650000
b110 (
b100 '
b10 &
b111111 #
0!
#655000
1!
#660000
b1 (
b1 *
b0 '
b1 ,
b0 +
b0 )
b0 &
b1000000 #
0!
#665000
1!
#670000
0.
1-
b10 (
b1 '
b1 &
b1000001 #
0!
#675000
1!
#680000
b1000010 #
0!
#685000
1!
#690000
b11 (
b10 '
b10 &
b1000011 #
0!
#695000
1!
#700000
b10 (
b1 '
b1 )
b0 &
b1000100 #
0!
#705000
1!
#710000
b11 (
b10 '
b1 &
b1000101 #
0!
#715000
1!
#720000
b1000110 #
0!
#725000
1!
#730000
b10 (
b11 '
b10 &
b1000111 #
0!
#735000
1!
#740000
b1 '
b0 &
b1001000 #
0!
#745000
1!
#750000
b11 (
b10 '
b1 &
b1001001 #
0!
#755000
1!
#760000
b1001010 #
0!
#765000
1!
#770000
b10 (
b11 '
b10 &
b1001011 #
0!
#775000
1!
#780000
b11 (
b10 '
b10 )
b0 &
b1001100 #
0!
#785000
1!
#790000
b10 (
b11 '
b1 &
b1001101 #
0!
#795000
1!
#800000
b1001110 #
0!
#805000
1!
#810000
1.
0-
b101 (
b100 '
b10 &
b1001111 #
0!
#815000
1!
#820000
0.
1-
b10 (
b10 *
b0 '
b1 +
b0 )
b0 &
b1010000 #
0!
#825000
1!
#830000
b11 (
b1 '
b1 &
b1010001 #
0!
#835000
1!
#840000
b1010010 #
0!
#845000
1!
#850000
1.
0-
b100 (
b10 '
b10 &
b1010011 #
0!
#855000
1!
#860000
0.
1-
b11 (
b1 '
b1 )
b0 &
b1010100 #
0!
#865000
1!
#870000
1.
0-
b100 (
b10 '
b1 &
b1010101 #
0!
#875000
1!
#880000
b1010110 #
0!
#885000
1!
#890000
b101 (
b11 '
b10 &
b1010111 #
0!
#895000
1!
#900000
0.
1-
b11 (
b1 '
b0 &
b1011000 #
0!
#905000
1!
#910000
1.
0-
b100 (
b10 '
b1 &
b1011001 #
0!
#915000
1!
#920000
b1011010 #
0!
#925000
1!
#930000
b101 (
b11 '
b10 &
b1011011 #
0!
#935000
1!
#940000
b100 (
b10 '
b10 )
b0 &
b1011100 #
0!
#945000
1!
#950000
b101 (
b11 '
b1 &
b1011101 #
0!
#955000
1!
#960000
b1011110 #
0!
#965000
1!
#970000
b110 (
b100 '
b10 &
b1011111 #
0!
#975000
1!
#980000
0.
1-
b10 (
b0 '
b0 )
b0 &
b1100000 #
0!
#985000
1!
#990000
b11 (
b1 '
b1 &
b1100001 #
0!
#995000
1!
#1000000
b1100010 #
0!
#1005000
1!
#1010000
1.
0-
b100 (
b10 '
b10 &
b1100011 #
0!
#1015000
1!
#1020000
0.
1-
b11 (
b1 '
b1 )
b0 &
b1100100 #
0!
#1025000
1!
#1030000
1.
0-
b100 (
b10 '
b1 &
b1100101 #
0!
#1035000
1!
#1040000
b1100110 #
0!
#1045000
1!
#1050000
b101 (
b11 '
b10 &
b1100111 #
0!
#1055000
1!
#1060000
0.
1-
b11 (
b1 '
b0 &
b1101000 #
0!
#1065000
1!
#1070000
1.
0-
b100 (
b10 '
b1 &
b1101001 #
0!
#1075000
1!
#1080000
b1101010 #
0!
#1085000
1!
#1090000
b101 (
b11 '
b10 &
b1101011 #
0!
#1095000
1!
#1100000
b100 (
b10 '
b10 )
b0 &
b1101100 #
0!
#1105000
1!
#1110000
b101 (
b11 '
b1 &
b1101101 #
0!
#1115000
1!
#1120000
b1101110 #
0!
#1125000
1!
#1130000
b110 (
b100 '
b10 &
b1101111 #
0!
#1135000
1!
#1140000
0.
1-
b11 (
b11 *
b0 '
b10 +
b0 )
b0 &
b1110000 #
0!
#1145000
1!
#1150000
b10 (
b1 '
b1 &
b1110001 #
0!
#1155000
1!
#1160000
b1110010 #
0!
#1165000
1!
#1170000
1.
0-
b101 (
b10 '
b10 &
b1110011 #
0!
#1175000
1!
#1180000
0.
1-
b10 (
b1 '
b1 )
b0 &
b1110100 #
0!
#1185000
1!
#1190000
1.
0-
b101 (
b10 '
b1 &
b1110101 #
0!
#1195000
1!
#1200000
b1110110 #
0!
#1205000
1!
#1210000
b110 (
b11 '
b10 &
b1110111 #
0!
#1215000
1!
#1220000
0.
1-
b10 (
b1 '
b0 &
b1111000 #
0!
#1225000
1!
#1230000
1.
0-
b101 (
b10 '
b1 &
b1111001 #
0!
#1235000
1!
#1240000
b1111010 #
0!
#1245000
1!
#1250000
b110 (
b11 '
b10 &
b1111011 #
0!
#1255000
1!
#1260000
b101 (
b10 '
b10 )
b0 &
b1111100 #
0!
#1265000
1!
#1270000
b110 (
b11 '
b1 &
b1111101 #
0!
#1275000
1!
#1280000
b1111110 #
0!
#1285000
1!
#1290000
b111 (
b100 '
b10 &
b1111111 #
0!
#1295000
1!
#1300000
b1 (
b1 *
b0 '
b0 +
b0 )
b0 &
b10000000 #
0!
#1305000
1!
#1310000
0.
1-
b10 (
b1 '
b1 &
b10000001 #
0!
#1315000
1!
#1320000
b10000010 #
0!
#1325000
1!
#1330000
b11 (
b10 '
b10 &
b10000011 #
0!
#1335000
1!
#1340000
b10 (
b1 '
b1 )
b0 &
b10000100 #
0!
#1345000
1!
#1350000
b11 (
b10 '
b1 &
b10000101 #
0!
#1355000
1!
#1360000
b10000110 #
0!
#1365000
1!
#1370000
b10 (
b11 '
b10 &
b10000111 #
0!
#1375000
1!
#1380000
b1 '
b0 &
b10001000 #
0!
#1385000
1!
#1390000
b11 (
b10 '
b1 &
b10001001 #
0!
#1395000
1!
#1400000
b10001010 #
0!
#1405000
1!
#1410000
b10 (
b11 '
b10 &
b10001011 #
0!
#1415000
1!
#1420000
b11 (
b10 '
b10 )
b0 &
b10001100 #
0!
#1425000
1!
#1430000
b10 (
b11 '
b1 &
b10001101 #
0!
#1435000
1!
#1440000
b10001110 #
0!
#1445000
1!
#1450000
1.
0-
b101 (
b100 '
b10 &
b10001111 #
0!
#1455000
1!
#1460000
0.
1-
b10 (
b10 *
b0 '
b1 +
b0 )
b0 &
b10010000 #
0!
#1465000
1!
#1470000
b11 (
b1 '
b1 &
b10010001 #
0!
#1475000
1!
#1480000
b10010010 #
0!
#1485000
1!
#1490000
1.
0-
b100 (
b10 '
b10 &
b10010011 #
0!
#1495000
1!
#1500000
0.
1-
b11 (
b1 '
b1 )
b0 &
b10010100 #
0!
#1505000
1!
#1510000
1.
0-
b100 (
b10 '
b1 &
b10010101 #
0!
#1515000
1!
#1520000
b10010110 #
0!
#1525000
1!
#1530000
b101 (
b11 '
b10 &
b10010111 #
0!
#1535000
1!
#1540000
0.
1-
b11 (
b1 '
b0 &
b10011000 #
0!
#1545000
1!
#1550000
1.
0-
b100 (
b10 '
b1 &
b10011001 #
0!
#1555000
1!
#1560000
b10011010 #
0!
#1565000
1!
#1570000
b101 (
b11 '
b10 &
b10011011 #
0!
#1575000
1!
#1580000
b100 (
b10 '
b10 )
b0 &
b10011100 #
0!
#1585000
1!
#1590000
b101 (
b11 '
b1 &
b10011101 #
0!
#1595000
1!
#1600000
b10011110 #
0!
#1605000
1!
#1610000
b110 (
b100 '
b10 &
b10011111 #
0!
#1615000
1!
#1620000
0.
1-
b10 (
b0 '
b0 )
b0 &
b10100000 #
0!
#1625000
1!
#1630000
b11 (
b1 '
b1 &
b10100001 #
0!
#1635000
1!
#1640000
b10100010 #
0!
#1645000
1!
#1650000
1.
0-
b100 (
b10 '
b10 &
b10100011 #
0!
#1655000
1!
#1660000
0.
1-
b11 (
b1 '
b1 )
b0 &
b10100100 #
0!
#1665000
1!
#1670000
1.
0-
b100 (
b10 '
b1 &
b10100101 #
0!
#1675000
1!
#1680000
b10100110 #
0!
#1685000
1!
#1690000
b101 (
b11 '
b10 &
b10100111 #
0!
#1695000
1!
#1700000
0.
1-
b11 (
b1 '
b0 &
b10101000 #
0!
#1705000
1!
#1710000
1.
0-
b100 (
b10 '
b1 &
b10101001 #
0!
#1715000
1!
#1720000
b10101010 #
0!
#1725000
1!
#1730000
b101 (
b11 '
b10 &
b10101011 #
0!
#1735000
1!
#1740000
b100 (
b10 '
b10 )
b0 &
b10101100 #
0!
#1745000
1!
#1750000
b101 (
b11 '
b1 &
b10101101 #
0!
#1755000
1!
#1760000
b10101110 #
0!
#1765000
1!
#1770000
b110 (
b100 '
b10 &
b10101111 #
0!
#1775000
1!
#1780000
0.
1-
b11 (
b11 *
b0 '
b10 +
b0 )
b0 &
b10110000 #
0!
#1785000
1!
#1790000
b10 (
b1 '
b1 &
b10110001 #
0!
#1795000
1!
#1800000
b10110010 #
0!
#1805000
1!
#1810000
1.
0-
b101 (
b10 '
b10 &
b10110011 #
0!
#1815000
1!
#1820000
0.
1-
b10 (
b1 '
b1 )
b0 &
b10110100 #
0!
#1825000
1!
#1830000
1.
0-
b101 (
b10 '
b1 &
b10110101 #
0!
#1835000
1!
#1840000
b10110110 #
0!
#1845000
1!
#1850000
b110 (
b11 '
b10 &
b10110111 #
0!
#1855000
1!
#1860000
0.
1-
b10 (
b1 '
b0 &
b10111000 #
0!
#1865000
1!
#1870000
1.
0-
b101 (
b10 '
b1 &
b10111001 #
0!
#1875000
1!
#1880000
b10111010 #
0!
#1885000
1!
#1890000
b110 (
b11 '
b10 &
b10111011 #
0!
#1895000
1!
#1900000
b101 (
b10 '
b10 )
b0 &
b10111100 #
0!
#1905000
1!
#1910000
b110 (
b11 '
b1 &
b10111101 #
0!
#1915000
1!
#1920000
b10111110 #
0!
#1925000
1!
#1930000
b111 (
b100 '
b10 &
b10111111 #
0!
#1935000
1!
#1940000
0.
1-
b10 (
b10 *
b0 '
b10 ,
b0 +
b0 )
b0 &
b11000000 #
0!
#1945000
1!
#1950000
b11 (
b1 '
b1 &
b11000001 #
0!
#1955000
1!
#1960000
b11000010 #
0!
#1965000
1!
#1970000
1.
0-
b100 (
b10 '
b10 &
b11000011 #
0!
#1975000
1!
#1980000
0.
1-
b11 (
b1 '
b1 )
b0 &
b11000100 #
0!
#1985000
1!
#1990000
1.
0-
b100 (
b10 '
b1 &
b11000101 #
0!
#1995000
1!
#2000000
b11000110 #
0!
#2005000
1!
#2010000
b101 (
b11 '
b10 &
b11000111 #
0!
#2015000
1!
#2020000
0.
1-
b11 (
b1 '
b0 &
b11001000 #
0!
#2025000
1!
#2030000
1.
0-
b100 (
b10 '
b1 &
b11001001 #
0!
#2035000
1!
#2040000
b11001010 #
0!
#2045000
1!
#2050000
b101 (
b11 '
b10 &
b11001011 #
0!
#2055000
1!
#2060000
b100 (
b10 '
b10 )
b0 &
b11001100 #
0!
#2065000
1!
#2070000
b101 (
b11 '
b1 &
b11001101 #
0!
#2075000
1!
#2080000
b11001110 #
0!
#2085000
1!
#2090000
b110 (
b100 '
b10 &
b11001111 #
0!
#2095000
1!
#2100000
0.
1-
b11 (
b11 *
b0 '
b1 +
b0 )
b0 &
b11010000 #
0!
#2105000
1!
#2110000
b10 (
b1 '
b1 &
b11010001 #
0!
#2115000
1!
#2120000
b11010010 #
0!
#2125000
1!
#2130000
1.
0-
b101 (
b10 '
b10 &
b11010011 #
0!
#2135000
1!
#2140000
0.
1-
b10 (
b1 '
b1 )
b0 &
b11010100 #
0!
#2145000
1!
#2150000
1.
0-
b101 (
b10 '
b1 &
b11010101 #
0!
#2155000
1!
#2160000
b11010110 #
0!
#2165000
1!
#2170000
b110 (
b11 '
b10 &
b11010111 #
0!
#2175000
1!
#2180000
0.
1-
b10 (
b1 '
b0 &
b11011000 #
0!
#2185000
1!
#2190000
1.
0-
b101 (
b10 '
b1 &
b11011001 #
0!
#2195000
1!
#2200000
b11011010 #
0!
#2205000
1!
#2210000
b110 (
b11 '
b10 &
b11011011 #
0!
#2215000
1!
#2220000
b101 (
b10 '
b10 )
b0 &
b11011100 #
0!
#2225000
1!
#2230000
b110 (
b11 '
b1 &
b11011101 #
0!
#2235000
1!
#2240000
b11011110 #
0!
#2245000
1!
#2250000
b111 (
b100 '
b10 &
b11011111 #
0!
#2255000
1!
#2260000
0.
1-
b11 (
b0 '
b0 )
b0 &
b11100000 #
0!
#2265000
1!
#2270000
b10 (
b1 '
b1 &
b11100001 #
0!
#2275000
1!
#2280000
b11100010 #
0!
#2285000
1!
#2290000
1.
0-
b101 (
b10 '
b10 &
b11100011 #
0!
#2295000
1!
#2300000
0.
1-
b10 (
b1 '
b1 )
b0 &
b11100100 #
0!
#2305000
1!
#2310000
1.
0-
b101 (
b10 '
b1 &
b11100101 #
0!
#2315000
1!
#2320000
b11100110 #
0!
#2325000
1!
#2330000
b110 (
b11 '
b10 &
b11100111 #
0!
#2335000
1!
#2340000
0.
1-
b10 (
b1 '
b0 &
b11101000 #
0!
#2345000
1!
#2350000
1.
0-
b101 (
b10 '
b1 &
b11101001 #
0!
#2355000
1!
#2360000
b11101010 #
0!
#2365000
1!
#2370000
b110 (
b11 '
b10 &
b11101011 #
0!
#2375000
1!
#2380000
b101 (
b10 '
b10 )
b0 &
b11101100 #
0!
#2385000
1!
#2390000
b110 (
b11 '
b1 &
b11101101 #
0!
#2395000
1!
#2400000
b11101110 #
0!
#2405000
1!
#2410000
b111 (
b100 '
b10 &
b11101111 #
0!
#2415000
1!
#2420000
b100 (
b100 *
b0 '
b10 +
b0 )
b0 &
b11110000 #
0!
#2425000
1!
#2430000
b101 (
b1 '
b1 &
b11110001 #
0!
#2435000
1!
#2440000
b11110010 #
0!
#2445000
1!
#2450000
b110 (
b10 '
b10 &
b11110011 #
0!
#2455000
1!
#2460000
b101 (
b1 '
b1 )
b0 &
b11110100 #
0!
#2465000
1!
#2470000
b110 (
b10 '
b1 &
b11110101 #
0!
#2475000
1!
#2480000
b11110110 #
0!
#2485000
1!
#2490000
b111 (
b11 '
b10 &
b11110111 #
0!
#2495000
1!
#2500000
b101 (
b1 '
b0 &
b11111000 #
0!
#2505000
1!
#2510000
b110 (
b10 '
b1 &
b11111001 #
0!
#2515000
1!
#2520000
b11111010 #
0!
#2525000
1!
#2530000
b111 (
b11 '
b10 &
b11111011 #
0!
#2535000
1!
#2540000
b110 (
b10 '
b10 )
b0 &
b11111100 #
0!
#2545000
1!
#2550000
b111 (
b11 '
b1 &
b11111101 #
0!
#2555000
1!
#2560000
b11111110 #
0!
